matplotx/__about__.py
matplotx/__init__.py
matplotx/_cli.py
matplotx/_contour.py
matplotx/_labels.py
matplotx/_optimize.py
matplotx/_spy.py
matplotx/styles/__init__.py
matplotx/styles/_aura.py
matplotx/styles/_ayu.py
matplotx/styles/_challenger_deep.py
matplotx/styles/_dhaitz.py
matplotx/styles/_dracula.py
matplotx/styles/_dufte.py
matplotx/styles/_github.py
matplotx/styles/_gruvbox.py
matplotx/styles/_helpers.py
matplotx/styles/_nord.py
matplotx/styles/_onedark.py
matplotx/styles/_solarized.py
matplotx/styles/_tableau.py
matplotx/styles/_tokyo_night.py
matplotx-0.3.10.dist-info/LICENSE
matplotx-0.3.10.dist-info/METADATA
matplotx-0.3.10.dist-info/WHEEL
matplotx-0.3.10.dist-info/entry_points.txt
matplotx-0.3.10.dist-info/top_level.txt
matplotx-0.3.10.dist-info/RECORD
