Metadata-Version: 2.1
Name: matplotx
Version: 0.3.10
Summary: Useful styles and extensions for Matplotlib
Author-email: Nico Schlömer <nico.schloemer@gmail.com>
License: The MIT License (MIT)
Project-URL: Code, https://github.com/nschloe/matplotx
Project-URL: Issues, https://github.com/nschloe/matplotx/issues
Project-URL: Funding, https://github.com/sponsors/nschloe
Classifier: Development Status :: 4 - Beta
Classifier: Framework :: Matplotlib
Classifier: License :: OSI Approved :: MIT License
Classifier: Operating System :: OS Independent
Classifier: Programming Language :: Python
Classifier: Programming Language :: Python :: 3
Classifier: Programming Language :: Python :: 3.7
Classifier: Programming Language :: Python :: 3.8
Classifier: Programming Language :: Python :: 3.9
Classifier: Programming Language :: Python :: 3.10
Classifier: Topic :: Utilities
Requires-Python: >=3.7
Provides-Extra: all
Provides-Extra: contour
Provides-Extra: spy
License-File: LICENSE
